tracker_exporter/__init__.py
tracker_exporter/_meta.py
tracker_exporter/_typing.py
tracker_exporter/config.py
tracker_exporter/etl.py
tracker_exporter/exceptions.py
tracker_exporter/main.py
tracker_exporter/models/__init__.py
tracker_exporter/models/base.py
tracker_exporter/models/issue.py
tracker_exporter/services/__init__.py
tracker_exporter/services/clickhouse.py
tracker_exporter/services/monitoring.py
tracker_exporter/services/tracker.py
tracker_exporter/state/__init__.py
tracker_exporter/state/backends.py
tracker_exporter/state/factory.py
tracker_exporter/state/managers.py
tracker_exporter/state/serializers.py
tracker_exporter/utils/__init__.py
tracker_exporter/utils/helpers.py
tracker_exporter-2.0.0.dist-info/LICENSE
tracker_exporter-2.0.0.dist-info/METADATA
tracker_exporter-2.0.0.dist-info/WHEEL
tracker_exporter-2.0.0.dist-info/entry_points.txt
tracker_exporter-2.0.0.dist-info/top_level.txt
tracker_exporter-2.0.0.dist-info/RECORD
