Metadata-Version: 2.1
Name: tracker-exporter
Version: 2.0.0
Summary: Yandex.Tracker issue metrics exporter
Home-page: https://github.com/akimrx/yandex-tracker-exporter
Download-URL: https://pypi.org/project/tracker-exporter/
Author: Akim Faskhutdinov
Author-email: akimstrong@yandex.ru
License: MIT
Keywords: yandex tracker exporter,yandex,tracker,etl,agile,cycle time
Platform: osx
Platform: linux
Classifier: Programming Language :: Python :: 3.10
Requires-Python: >=3.10
License-File: LICENSE
Requires-Dist: yandex-tracker-client ==2.*
Requires-Dist: boto3 ==1.34.*
Requires-Dist: redis ==5.0.*
Requires-Dist: datadog ==0.47.*
Requires-Dist: APScheduler ==3.10.*
Requires-Dist: requests ==2.31.*
Requires-Dist: numpy ==1.26.0
Requires-Dist: pandas ==2.1.1
Requires-Dist: businesstimedelta ==1.0.1
Requires-Dist: holidays ==0.34
Requires-Dist: sentry-sdk ==1.32.*
Requires-Dist: python-dotenv
Requires-Dist: pydantic ==2.4.*
Requires-Dist: pydantic-settings ==2.0.*
Requires-Dist: psutil ==5.9.*
